{
  "_class": "text",
  "attributedString": {
    "_class": "attributedString",
    "attributes": [
      {
        "_class": "stringAttribute",
        "attributes": {
          "MSAttributedStringColorAttribute": {
            "_class": "color",
            "alpha": 1,
            "blue": 0.07843137255,
            "green": 0.07843137255,
            "red": 0.07843137255
          },
          "MSAttributedStringFontAttribute": {
            "_class": "fontDescriptor",
            "attributes": {
              "name": "Montserrat-Light",
              "size": 14
            }
          },
          "kerning": 0,
          "paragraphStyle": {
            "_class": "paragraphStyle",
            "alignment": 0,
            "allowsDefaultTighteningForTruncation": 0,
            "maximumLineHeight": 26,
            "minimumLineHeight": 26
          }
        },
        "length": 18,
        "location": 0
      }
    ],
    "string": "- Seleccione uno -"
  },
  "automaticallyDrawOnUnderlyingPath": false,
  "booleanOperation": 0,
  "clippingMaskMode": 0,
  "do_objectID": "5BDE60C7-09F1-40D2-B600-423752E1D9C8",
  "dontSynchroniseWithSymbol": false,
  "exportOptions": {
    "_class": "exportOptions",
    "do_objectID": "1DC8C920-B0FB-4798-9A20-F1518E991B30",
    "exportFormats": [
    ],
    "includedLayerIds": [
    ],
    "layerOptions": 0,
    "shouldTrim": false
  },
  "frame": {
    "_class": "rect",
    "constrainProportions": false,
    "do_objectID": "E0433556-95E3-46C5-A72D-5FE0EEBF7A56",
    "height": 26,
    "width": 123,
    "x": 15,
    "y": 11
  },
  "glyphBounds": "{{0, 8}, {123, 12}}",
  "hasClippingMask": false,
  "isFixedToViewport": false,
  "isFlippedHorizontal": false,
  "isFlippedVertical": false,
  "isLocked": false,
  "isVisible": true,
  "layerListExpandedType": 0,
  "lineSpacingBehaviour": 2,
  "name": "- Seleccione uno -",
  "nameIsFixed": false,
  "resizingConstraint": 11,
  "resizingType": 1,
  "rotation": 0,
  "sharedStyleID": "A2F08008-949A-4D35-930A-183613990537",
  "shouldBreakMaskChain": false,
  "style": {
    "_class": "style",
    "do_objectID": "AC5B9A2C-67ED-4624-8BE7-86CF4AAA98E0",
    "endMarkerType": 0,
    "miterLimit": 10,
    "startMarkerType": 0,
    "textStyle": {
      "_class": "textStyle",
      "do_objectID": "C55BD3B3-E7B5-44DA-85B9-14AE89ACA8AA",
      "encodedAttributes": {
        "MSAttributedStringColorAttribute": {
          "_class": "color",
          "alpha": 1,
          "blue": 0.07843137255,
          "green": 0.07843137255,
          "red": 0.07843137255
        },
        "MSAttributedStringFontAttribute": {
          "_class": "fontDescriptor",
          "attributes": {
            "name": "Montserrat-Light",
            "size": 14
          }
        },
        "kerning": 0,
        "paragraphStyle": {
          "_class": "paragraphStyle",
          "alignment": 0,
          "allowsDefaultTighteningForTruncation": 0,
          "maximumLineHeight": 26,
          "minimumLineHeight": 26
        }
      },
      "verticalAlignment": 0
    },
    "windingRule": 1
  },
  "textBehaviour": 0,
  "userInfo": {
    "com.animaapp.stc-sketch-plugin": {
      "kModelPropertiesKey": {
        "isAutoWidth": 1
      }
    }
  }
}