{
  "_class": "text",
  "attributedString": {
    "_class": "attributedString",
    "attributes": [
      {
        "_class": "stringAttribute",
        "attributes": {
          "MSAttributedStringColorAttribute": {
            "_class": "color",
            "alpha": 1,
            "blue": 0.07843137255,
            "green": 0.07843137255,
            "red": 0.07843137255
          },
          "MSAttributedStringFontAttribute": {
            "_class": "fontDescriptor",
            "attributes": {
              "name": "Montserrat-Light",
              "size": 14
            }
          },
          "kerning": 0,
          "paragraphStyle": {
            "_class": "paragraphStyle",
            "alignment": 0,
            "allowsDefaultTighteningForTruncation": 0,
            "maximumLineHeight": 26,
            "minimumLineHeight": 26
          }
        },
        "length": 7,
        "location": 0
      }
    ],
    "string": "Writing"
  },
  "automaticallyDrawOnUnderlyingPath": false,
  "booleanOperation": 0,
  "clippingMaskMode": 0,
  "do_objectID": "043A08FA-013D-4F2E-9FEF-1AB3DCEAFF55",
  "dontSynchroniseWithSymbol": false,
  "exportOptions": {
    "_class": "exportOptions",
    "do_objectID": "2B530053-D23A-4992-BDA6-AAA754F62602",
    "exportFormats": [
    ],
    "includedLayerIds": [
    ],
    "layerOptions": 0,
    "shouldTrim": false
  },
  "frame": {
    "_class": "rect",
    "constrainProportions": false,
    "do_objectID": "A6338808-A30D-4A19-A19F-D558CA84AA58",
    "height": 26,
    "width": 51,
    "x": 20,
    "y": 11
  },
  "glyphBounds": "{{0, 0}, {50, 21}}",
  "hasClippingMask": false,
  "isFixedToViewport": false,
  "isFlippedHorizontal": false,
  "isFlippedVertical": false,
  "isLocked": false,
  "isVisible": true,
  "layerListExpandedType": 0,
  "lineSpacingBehaviour": 2,
  "name": "Writing",
  "nameIsFixed": false,
  "resizingConstraint": 11,
  "resizingType": 1,
  "rotation": 0,
  "sharedStyleID": "5CD2948C-6A31-49D0-9629-12207D4480D6",
  "shouldBreakMaskChain": false,
  "style": {
    "_class": "style",
    "do_objectID": "4B938B9D-B925-4998-AB7E-87980BD8C92A",
    "endMarkerType": 0,
    "miterLimit": 10,
    "startMarkerType": 0,
    "textStyle": {
      "_class": "textStyle",
      "do_objectID": "673A73A0-2F1C-44F6-848F-4FDB0A2B151A",
      "encodedAttributes": {
        "MSAttributedStringColorAttribute": {
          "_class": "color",
          "alpha": 1,
          "blue": 0.07843137255,
          "green": 0.07843137255,
          "red": 0.07843137255
        },
        "MSAttributedStringFontAttribute": {
          "_class": "fontDescriptor",
          "attributes": {
            "name": "Montserrat-Light",
            "size": 14
          }
        },
        "kerning": 0,
        "paragraphStyle": {
          "_class": "paragraphStyle",
          "alignment": 0,
          "allowsDefaultTighteningForTruncation": 0,
          "maximumLineHeight": 26,
          "minimumLineHeight": 26
        }
      },
      "verticalAlignment": 0
    },
    "windingRule": 1
  },
  "textBehaviour": 0
}