{
  "_class": "symbolInstance",
  "booleanOperation": -1,
  "clippingMaskMode": 0,
  "do_objectID": "2B14BF44-EEF3-4BE2-A268-2DE6675A30C8",
  "exportOptions": {
    "_class": "exportOptions",
    "do_objectID": "37BAA0A7-A693-4ED3-8195-AA37C6F34A3B",
    "exportFormats": [
    ],
    "includedLayerIds": [
    ],
    "layerOptions": 0,
    "shouldTrim": false
  },
  "frame": {
    "_class": "rect",
    "constrainProportions": false,
    "do_objectID": "F594CB0A-6F53-422A-BBE8-50D16BFD1012",
    "height": 60,
    "width": 961,
    "x": 231,
    "y": 492
  },
  "hasClippingMask": false,
  "horizontalSpacing": 0,
  "isFixedToViewport": false,
  "isFlippedHorizontal": false,
  "isFlippedVertical": false,
  "isLocked": false,
  "isVisible": true,
  "layerListExpandedType": 0,
  "name": "row_files",
  "nameIsFixed": false,
  "overrideValues": [
  ],
  "resizingConstraint": 63,
  "resizingType": 0,
  "rotation": 0,
  "scale": 1,
  "shouldBreakMaskChain": false,
  "style": {
    "_class": "style",
    "do_objectID": "985046A4-A7E4-462B-994A-EEAD69615D88",
    "endMarkerType": 0,
    "miterLimit": 10,
    "startMarkerType": 0,
    "windingRule": 1
  },
  "symbolID": "45562E7F-5CA6-4DCD-B1CD-35052E387C83",
  "verticalSpacing": 0
}