{
  "_class": "symbolInstance",
  "booleanOperation": -1,
  "clippingMaskMode": 0,
  "do_objectID": "F1B4AF55-DD82-4437-980F-A822B90D8B60",
  "exportOptions": {
    "_class": "exportOptions",
    "do_objectID": "5B3CC0DB-C443-4928-8625-04BE522422B0",
    "exportFormats": [
    ],
    "includedLayerIds": [
    ],
    "layerOptions": 0,
    "shouldTrim": false
  },
  "frame": {
    "_class": "rect",
    "constrainProportions": false,
    "do_objectID": "57CB8C57-55AA-4136-AE16-2FC1856DCE72",
    "height": 60,
    "width": 842,
    "x": 289,
    "y": 1410
  },
  "hasClippingMask": false,
  "horizontalSpacing": 0,
  "isFixedToViewport": false,
  "isFlippedHorizontal": false,
  "isFlippedVertical": false,
  "isLocked": false,
  "isVisible": true,
  "layerListExpandedType": 0,
  "name": "Row_facultades",
  "nameIsFixed": false,
  "overrideValues": [
  ],
  "resizingConstraint": 63,
  "resizingType": 0,
  "rotation": 0,
  "scale": 1,
  "shouldBreakMaskChain": false,
  "style": {
    "_class": "style",
    "do_objectID": "6F460B40-AD81-407E-BF2F-FBA5636F0B62",
    "endMarkerType": 0,
    "miterLimit": 10,
    "startMarkerType": 0,
    "windingRule": 1
  },
  "symbolID": "70D1BEBE-1738-4B80-803F-F9678BAA74FF",
  "verticalSpacing": 0
}